odoo/addons/hr_expense_tier_validation/README.rst
odoo/addons/hr_expense_tier_validation/__init__.py
odoo/addons/hr_expense_tier_validation/__manifest__.py
odoo/addons/hr_expense_tier_validation/i18n/hr_expense_tier_validation.pot
odoo/addons/hr_expense_tier_validation/models/__init__.py
odoo/addons/hr_expense_tier_validation/models/hr_expense.py
odoo/addons/hr_expense_tier_validation/models/hr_expense_sheet.py
odoo/addons/hr_expense_tier_validation/models/tier_definition.py
odoo/addons/hr_expense_tier_validation/readme/CONFIGURE.rst
odoo/addons/hr_expense_tier_validation/readme/CONTRIBUTORS.rst
odoo/addons/hr_expense_tier_validation/readme/DESCRIPTION.rst
odoo/addons/hr_expense_tier_validation/readme/INSTALL.rst
odoo/addons/hr_expense_tier_validation/readme/USAGE.rst
odoo/addons/hr_expense_tier_validation/static/description/icon.png
odoo/addons/hr_expense_tier_validation/static/description/index.html
odoo/addons/hr_expense_tier_validation/tests/__init__.py
odoo/addons/hr_expense_tier_validation/tests/test_hr_expense_tier_validation.py
odoo/addons/hr_expense_tier_validation/views/hr_expense_sheet_view.xml
odoo14_addon_hr_expense_tier_validation-14.0.1.2.1.dist-info/METADATA
odoo14_addon_hr_expense_tier_validation-14.0.1.2.1.dist-info/WHEEL
odoo14_addon_hr_expense_tier_validation-14.0.1.2.1.dist-info/top_level.txt
odoo14_addon_hr_expense_tier_validation-14.0.1.2.1.dist-info/RECORD
